odoo9_addon_delivery_carrier_label_batch-9.0.1.0.0.99.dev22-nspkg.pth
odoo_addons/delivery_carrier_label_batch/README.rst
odoo_addons/delivery_carrier_label_batch/__init__.py
odoo_addons/delivery_carrier_label_batch/__openerp__.py
odoo_addons/delivery_carrier_label_batch/pdf_utils.py
odoo_addons/delivery_carrier_label_batch/zpl_utils.py
odoo_addons/delivery_carrier_label_batch/i18n/de.po
odoo_addons/delivery_carrier_label_batch/i18n/delivery_carrier_label_batch.pot
odoo_addons/delivery_carrier_label_batch/i18n/fr.po
odoo_addons/delivery_carrier_label_batch/models/__init__.py
odoo_addons/delivery_carrier_label_batch/models/stock_batch_picking.py
odoo_addons/delivery_carrier_label_batch/static/description/icon.png
odoo_addons/delivery_carrier_label_batch/tests/__init__.py
odoo_addons/delivery_carrier_label_batch/tests/dummy.pdf
odoo_addons/delivery_carrier_label_batch/tests/test_generate_labels.py
odoo_addons/delivery_carrier_label_batch/views/stock_batch_picking.xml
odoo_addons/delivery_carrier_label_batch/wizard/__init__.py
odoo_addons/delivery_carrier_label_batch/wizard/apply_carrier.py
odoo_addons/delivery_carrier_label_batch/wizard/apply_carrier_view.xml
odoo_addons/delivery_carrier_label_batch/wizard/generate_labels.py
odoo_addons/delivery_carrier_label_batch/wizard/generate_labels_view.xml
odoo9_addon_delivery_carrier_label_batch-9.0.1.0.0.99.dev22.dist-info/METADATA
odoo9_addon_delivery_carrier_label_batch-9.0.1.0.0.99.dev22.dist-info/WHEEL
odoo9_addon_delivery_carrier_label_batch-9.0.1.0.0.99.dev22.dist-info/namespace_packages.txt
odoo9_addon_delivery_carrier_label_batch-9.0.1.0.0.99.dev22.dist-info/top_level.txt
odoo9_addon_delivery_carrier_label_batch-9.0.1.0.0.99.dev22.dist-info/RECORD
